.gitattributes
.gitignore
.travis.yml
3.png
4.png
Dockerfile
LICENSE
README.md
b-1.png
b.png
docker-compose.yml
qq.png
requirements.txt
setup.py
docs/.nojekyll
docs/_coverpage.md
docs/_sidebar.md
docs/index.html
docs/design/README.md
docs/functions/README.md
docs/home/README.md
docs/pics/client+server.svg
docs/pics/feature_matching_sample.png
docs/pics/screen.png
docs/pics/wechat_logo.png
docs/plan/README.md
docs/usage/client+server.md
docs/usage/normal.md
findit/__init__.py
findit/core.py
findit/logger.py
findit/toolbox.py
findit.egg-info/PKG-INFO
findit.egg-info/SOURCES.txt
findit.egg-info/dependency_links.txt
findit.egg-info/requires.txt
findit.egg-info/top_level.txt
findit/engine/__init__.py
findit/engine/base.py
findit/engine/feature.py
findit/engine/ocr.py
findit/engine/sim.py
findit/engine/template.py
findit/server/__init__.py
findit/server/__main__.py
findit/server/config.py
findit/server/router.py
findit/server/utils.py
sample/.DS_Store
sample/demo.py
sample/how_feature_matching_works.py
sample/how_ocr_works.py
sample/short.py
sample/pics/album_logo.png
sample/pics/app_store_logo.png
sample/pics/music_logo.png
sample/pics/screen.png
sample/pics/wechat_logo.png
tests/test_server.py