Metadata-Version: 2.1
Name: findit
Version: 0.5.9
Summary: find target icon on your picture, and get its position
Home-page: https://github.com/williamfzc/findit
Author: williamfzc
Author-email: fengzc@vip.qq.com
License: UNKNOWN
Platform: UNKNOWN
Requires-Python: >=3.6
Provides-Extra: web
